bulky/__init__.py
bulky/consts.py
bulky/errors.py
bulky/types.py
bulky/functions/__init__.py
bulky/functions/insert.py
bulky/functions/update.py
bulky/internals/__init__.py
bulky/internals/sql.py
bulky/internals/utils.py
bulky-1.0.1.dist-info/LICENSE
bulky-1.0.1.dist-info/METADATA
bulky-1.0.1.dist-info/WHEEL
bulky-1.0.1.dist-info/top_level.txt
bulky-1.0.1.dist-info/RECORD
