Metadata-Version: 2.1
Name: bulky
Version: 1.0.1
Summary: A library with bulk operations on SQLAlchemy and PostgreSQL
Home-page: UNKNOWN
Author: Alexander Sidorov
Author-email: alex.n.sidorov@gmail.com
License: UNKNOWN
Keywords: bulk db postgresqlsqlalchemy sqlalchemy-core
Platform: UNKNOWN
Classifier: Development Status :: 5 - Production/Stable
Classifier: Environment :: Console
Classifier: Intended Audience :: Developers
Classifier: License :: OSI Approved :: Apache Software License
Classifier: Operating System :: MacOS :: MacOS X
Classifier: Operating System :: POSIX :: Linux
Classifier: Programming Language :: Python :: 3.6
Classifier: Programming Language :: Python :: 3.7
Classifier: Topic :: Database
Classifier: Topic :: Software Development :: Libraries :: Python Modules
Requires-Python: >=3.6, <4
Requires-Dist: SQLAlchemy (>=1.1)
Requires-Dist: psycopg2-binary (>=2.7)
Requires-Dist: Jinja2 (>=2.10.1)
Requires-Dist: typeguard (>=2)
